digital_twinning/__init__.py
digital_twinning/model_updating/__init__.py
digital_twinning/model_updating/digital_twin.py
digital_twinning/model_updating/multibuilding_update.py
digital_twinning/predictive_models/__init__.py
digital_twinning/predictive_models/dnn_model.py
digital_twinning/predictive_models/gbt_model.py
digital_twinning/predictive_models/linreg_model.py
digital_twinning/predictive_models/predictive_model.py
digital_twinning/utils/__init__.py
digital_twinning/utils/gbt_plot_utils.py
digital_twinning/utils/object_utils.py
digital_twinning/utils/plotting_functions.py
digital_twinning/utils/utils.py
digital_twinning-0.1.7.dist-info/licenses/LICENSE
digital_twinning-0.1.7.dist-info/METADATA
digital_twinning-0.1.7.dist-info/WHEEL
digital_twinning-0.1.7.dist-info/top_level.txt
digital_twinning-0.1.7.dist-info/RECORD
